MANIFEST.in
README.md
setup.py
veripress/__init__.py
veripress/__main__.py
veripress/helpers.py
veripress.egg-info/PKG-INFO
veripress.egg-info/SOURCES.txt
veripress.egg-info/dependency_links.txt
veripress.egg-info/entry_points.txt
veripress.egg-info/requires.txt
veripress.egg-info/top_level.txt
veripress/api/__init__.py
veripress/api/handlers.py
veripress/model/__init__.py
veripress/model/models.py
veripress/model/parsers.py
veripress/model/storages.py
veripress/model/toc.py
veripress/view/__init__.py
veripress/view/views.py
veripress_cli/__init__.py
veripress_cli/deploy.py
veripress_cli/generate.py
veripress_cli/helpers.py
veripress_cli/init.py
veripress_cli/serve.py
veripress_cli/theme.py
veripress_cli/defaults/config.py
veripress_cli/defaults/site.json
veripress_cli/defaults/static/favicon.ico