Metadata-Version: 2.1
Name: veripress
Version: 1.0.11
Summary: A blog engine for hackers.
Home-page: https://github.com/veripress/veripress
Author: Richard Chien
Author-email: richardchienthebest@gmail.com
License: MIT License
Platform: any
Classifier: Development Status :: 5 - Production/Stable
Classifier: Framework :: Flask
Classifier: License :: OSI Approved :: MIT License
Classifier: Operating System :: OS Independent
Classifier: Programming Language :: Python :: 3
Classifier: Programming Language :: Python :: 3 :: Only
Requires-Python: >=3.4
